[
    {
        "title": "Concussion Grenades",
        "weapon": {
            "range": 1,
            "dice": [
                "black"
            ],
            "keywords": [
                {
                    "text": "Blast"
                }
            ]
        },
        "kind": "grenades",
        "points": 5,
        "products": [
            {
                "product_id": "core",
                "count": 4
            }
        ]
    }, {
        "title": "Fragmentation Grenades",
        "weapon": {
            "range": 1,
            "dice": [
                "red"
            ],
            "surges": {
                "attack": "crit"
            }
        },
        "kind": "grenades",
        "points": 5,
        "products": [
            {
                "product_id": "wookie"
            }, {
                "product_id": "pathfinder"
            }
        ]
    }, {
        "title": "Impact Grenades",
        "weapon": {
            "range": 1,
            "dice": [
                "black"
            ],
            "keywords": [
                {
                    "text": "Impact",
                    "value": 1
                }
            ]
        },
        "kind": "grenades",
        "points": 5,
        "products": [
            {
                "product_id": "rebel"
            }, {
                "product_id": "fleet"
            }
        ]
    }
]